ionoscloud_cert_manager/__init__.py
ionoscloud_cert_manager/api_client.py
ionoscloud_cert_manager/api_response.py
ionoscloud_cert_manager/configuration.py
ionoscloud_cert_manager/exceptions.py
ionoscloud_cert_manager/rest.py
ionoscloud_cert_manager/test-driver.py
ionoscloud_cert_manager/api/__init__.py
ionoscloud_cert_manager/api/auto_certificate_api.py
ionoscloud_cert_manager/api/certificate_api.py
ionoscloud_cert_manager/api/certificates_api.py
ionoscloud_cert_manager/api/information_api.py
ionoscloud_cert_manager/api/provider_api.py
ionoscloud_cert_manager/models/__init__.py
ionoscloud_cert_manager/models/api_info_dto.py
ionoscloud_cert_manager/models/auto_certificate.py
ionoscloud_cert_manager/models/auto_certificate_create.py
ionoscloud_cert_manager/models/auto_certificate_patch.py
ionoscloud_cert_manager/models/auto_certificate_read.py
ionoscloud_cert_manager/models/auto_certificate_read_list.py
ionoscloud_cert_manager/models/auto_certificate_read_list_all_of.py
ionoscloud_cert_manager/models/certificate.py
ionoscloud_cert_manager/models/certificate_collection_dto.py
ionoscloud_cert_manager/models/certificate_collection_dto_links.py
ionoscloud_cert_manager/models/certificate_create.py
ionoscloud_cert_manager/models/certificate_dto.py
ionoscloud_cert_manager/models/certificate_patch.py
ionoscloud_cert_manager/models/certificate_patch_dto.py
ionoscloud_cert_manager/models/certificate_patch_properties_dto.py
ionoscloud_cert_manager/models/certificate_post_dto.py
ionoscloud_cert_manager/models/certificate_post_properties_dto.py
ionoscloud_cert_manager/models/certificate_properties_dto.py
ionoscloud_cert_manager/models/certificate_read.py
ionoscloud_cert_manager/models/certificate_read_list.py
ionoscloud_cert_manager/models/certificate_read_list_all_of.py
ionoscloud_cert_manager/models/config_property_dto.py
ionoscloud_cert_manager/models/connection.py
ionoscloud_cert_manager/models/day_of_the_week.py
ionoscloud_cert_manager/models/error.py
ionoscloud_cert_manager-2.0.0.dist-info/LICENSE
ionoscloud_cert_manager-2.0.0.dist-info/METADATA
ionoscloud_cert_manager-2.0.0.dist-info/WHEEL
ionoscloud_cert_manager-2.0.0.dist-info/top_level.txt
ionoscloud_cert_manager-2.0.0.dist-info/RECORD
